Pyspectr/__init__.py
Pyspectr/decay_fitter.py
Pyspectr/exceptions.py
Pyspectr/hisfile.py
Pyspectr/histogram.py
Pyspectr/peak_fitter.py
Pyspectr/plotscatter.py
Pyspectr/plotter.py
Pyspectr/pydamm.py
Pyspectr-0.2.3.data/scripts/plotscatter.py
Pyspectr-0.2.3.data/scripts/py_grow_decay.py
Pyspectr-0.2.3.data/scripts/spectrum_fitter.py
Pyspectr-0.2.3.dist-info/METADATA
Pyspectr-0.2.3.dist-info/RECORD
Pyspectr-0.2.3.dist-info/WHEEL
Pyspectr-0.2.3.dist-info/top_level.txt
