Metadata-Version: 2.1
Name: Pyspectr
Version: 0.2.3
Summary: Useful spectroscopic tools
Home-page: https://github.com/ntbrewer/Pyspectr
Author: Nathan Brewer
Author-email: brewer.nathant@gmail.com
License: LICENSE.txt
Platform: UNKNOWN
Classifier: Development Status :: 5 - Production/Stable
Classifier: Intended Audience :: Science/Research
Classifier: License :: OSI Approved :: GNU General Public License v3 (GPLv3)
Classifier: Programming Language :: Python :: 3.5
Classifier: Topic :: Scientific/Engineering :: Physics
Requires: matplotlib
Requires: numpy
Requires: lmfit
